<?xml version="1.0" encoding="UTF-8"?>
<!-- $Id: dataAccessContext-hibernate.xml,v 1.5 2008/01/16 05:18:56 abel Exp $ -->
<!DOCTYPE beans PUBLIC "-//SPRING//DTD BEAN 2.0//EN" "http://www.springframework.org/dtd/spring-beans-2.0.dtd">
<beans default-autowire="byName" default-lazy-init="false">

	<bean id="dataSource"
		class="com.mchange.v2.c3p0.ComboPooledDataSource"
		destroy-method="close">
		<property name="driverClass" value="${jdbc.driverClassName}" />
		<property name="jdbcUrl" value="${jdbc.url}" />
		<property name="user" value="${jdbc.username}" />
		<property name="password" value="${jdbc.password}" />
		<property name="minPoolSize" value="${jdbc.minPoolSize}"/>
		<property name="maxPoolSize" value="${jdbc.maxPoolSize}"/>
		<property name="initialPoolSize" value="${jdbc.initialPoolSize}"/>
		<property name="acquireIncrement" value="${jdbc.acquireIncrement}"/>
		<property name="maxIdleTime" value="${jdbc.maxIdleTime}"/>
		<property name="maxStatements" value="${jdbc.maxStatements}"/>
		<property name="idleConnectionTestPeriod" value="${jdbc.idleConnectionTestPeriod}"/>
		<property name="acquireRetryAttempts" value="${jdbc.acquireRetryAttempts}"/>
		<property name="breakAfterAcquireFailure" value="${jdbc.breakAfterAcquireFailure}"/>
		<property name="testConnectionOnCheckout" value="${jdbc.testConnectionOnCheckout}"/>
	</bean>

	<bean id="sessionFactory"
		class="org.springframework.orm.hibernate3.LocalSessionFactoryBean">
		<property name="dataSource">
			<ref bean="dataSource" />
		</property>
		<property name="mappingDirectoryLocations">
			<!--property name="mappingResources" -->
			<list>
				<value>
					classpath:/com/yesiic/webswith/model/
				</value>
				<value>
					classpath:/com/yesiic/person/model/
				</value>
				<value>
					classpath:/com/yesiic/company/model/
				</value>
				<value>
					classpath:/com/yesiic/base/model/
				</value>
			</list>
		</property>
		<property name="hibernateProperties">
			<props>
				<!-- prop key="hibernate.dialect">org.hibernate.dialect.MySQLDialect</prop//-->
				<prop key="hibernate.dialect">
					${jdbc.hibernate.dialet}
				</prop>
				<prop key="hibernate.show_sql">${jdbc.sql.show}</prop>
				<prop key="hibernate.generate_statistics">true</prop>
				<prop key="hibernate.jdbc.use_streams_for_binary">
					true
				</prop>
				<prop key="hibernate.cache.use_query_cache">false</prop>
				<prop key="hibernate.cache.use_second_level_cache">
					false
				</prop>
				<!--prop key="hibernate.cache.provider_class">
					org.hibernate.cache.EhCacheProvider
				</prop-->
			</props>
		</property>
	</bean>

	<!--Hibernate TransactionManager-->
	<bean id="transactionManager"
		class="org.springframework.orm.hibernate3.HibernateTransactionManager">
		<property name="sessionFactory" ref="sessionFactory" />
	</bean>
</beans>
